setup.cfg
setup.py
pypplapi/__init__.py
pypplapi/module.py
pypplapi.egg-info/PKG-INFO
pypplapi.egg-info/SOURCES.txt
pypplapi.egg-info/dependency_links.txt
pypplapi.egg-info/not-zip-safe
pypplapi.egg-info/requires.txt
pypplapi.egg-info/top_level.txt