Metadata-Version: 1.0
Name: pypplapi
Version: 0.1
Summary: A Python wrapper around pplapi.
Home-page: https://github.com/rudimk/pypplapi
Author: Rudraksh MK
Author-email: rudraksh.mk@gmail.com
License: MIT
Platform: UNKNOWN
